coherence/__init__.py
coherence/aggregator.py
coherence/ai.py
coherence/cache_service_messages_v1_pb2.py
coherence/cache_service_messages_v1_pb2.pyi
coherence/cache_service_messages_v1_pb2_grpc.py
coherence/client.py
coherence/common_messages_v1_pb2.py
coherence/common_messages_v1_pb2.pyi
coherence/common_messages_v1_pb2_grpc.py
coherence/comparator.py
coherence/entry.py
coherence/event.py
coherence/extractor.py
coherence/filter.py
coherence/local_cache.py
coherence/messages_pb2.py
coherence/messages_pb2.pyi
coherence/messages_pb2_grpc.py
coherence/nslookup.py
coherence/processor.py
coherence/proxy_service_messages_v1_pb2.py
coherence/proxy_service_messages_v1_pb2.pyi
coherence/proxy_service_messages_v1_pb2_grpc.py
coherence/proxy_service_v1_pb2.py
coherence/proxy_service_v1_pb2.pyi
coherence/proxy_service_v1_pb2_grpc.py
coherence/serialization.py
coherence/services_pb2.py
coherence/services_pb2.pyi
coherence/services_pb2_grpc.py
coherence/util.py
coherence_client-2.0.4.dist-info/LICENSE.txt
coherence_client-2.0.4.dist-info/METADATA
coherence_client-2.0.4.dist-info/WHEEL
coherence_client-2.0.4.dist-info/RECORD
