Metadata-Version: 2.3
Name: coherence-client
Version: 2.0.4
Summary: The Coherence Python Client allows Python applications to act as cache clients to a Coherence Cluster using Google's gRPC framework as the network transport.
Author: Oracle
Author-email: dhiru.pandey@oracle.com
Requires-Python: >=3.9,<4.0
Classifier: Development Status :: 5 - Production/Stable
Classifier: License :: OSI Approved :: Universal Permissive License (UPL)
Classifier: Operating System :: OS Independent
Classifier: Programming Language :: Python :: 3
Classifier: Programming Language :: Python :: 3.9
Classifier: Programming Language :: Python :: 3.10
Classifier: Programming Language :: Python :: 3.11
Classifier: Programming Language :: Python :: 3.12
Classifier: Programming Language :: Python :: 3.13
Requires-Dist: grpcio (==1.73.0)
Requires-Dist: grpcio-tools (==1.71.0)
Requires-Dist: jsonpickle (>=3.0,<4.2)
Requires-Dist: numpy (==2.0.2)
Requires-Dist: protobuf (==5.29.5)
Requires-Dist: pymitter (>=0.4,<1.1)
Requires-Dist: pympler (==1.1)
Requires-Dist: types-protobuf (==6.30.2.20250703)
Requires-Dist: typing-extensions (>=4.11,<4.15)
Project-URL: Homepage, https://github.com/oracle/coherence-py-client
Project-URL: Repository, https://github.com/oracle/coherence-py-client
